mindtrace/storage/__init__.py
mindtrace/storage/base.py
mindtrace/storage/gcs.py
mindtrace_storage-0.8.0.dist-info/licenses/LICENSE
mindtrace_storage-0.8.0.dist-info/METADATA
mindtrace_storage-0.8.0.dist-info/WHEEL
mindtrace_storage-0.8.0.dist-info/top_level.txt
mindtrace_storage-0.8.0.dist-info/RECORD
